ibm_watson_openscale/version.py
ibm_watson_openscale/service_providers.py
ibm_watson_openscale/data_marts.py
ibm_watson_openscale/integrated_systems.py
ibm_watson_openscale/client.py
ibm_watson_openscale/subscriptions.py
ibm_watson_openscale/wos.py
ibm_watson_openscale/__init__.py
ibm_watson_openscale/monitor_instances.py
ibm_watson_openscale/model.py
ibm_watson_openscale/mrm.py
ibm_watson_openscale/custom_monitor.py
ibm_watson_openscale/mrm_monitoring.py
ibm_watson_openscale/runs.py
ibm_watson_openscale/data_sets.py
ibm_watson_openscale/monitor_definitions.py
ibm_watson_openscale/base_classes/__init__.py
ibm_watson_openscale/base_classes/common.py
ibm_watson_openscale/base_classes/tables.py
ibm_watson_openscale/base_classes/watson_open_scale_v2.py
ibm_watson_openscale/base_classes/models/__init__.py
ibm_watson_openscale/base_classes/models/known_service_model.py
ibm_watson_openscale/base_classes/models/engine_models/__init__.py
ibm_watson_openscale/base_classes/models/engine_models/wml.py
ibm_watson_openscale/callbacks/__init__.py
ibm_watson_openscale/callbacks/langchain.py
ibm_watson_openscale/entity/subscription.py
ibm_watson_openscale/entity/__init__.py
ibm_watson_openscale/entity/drift_v2_monitor_instance.py
ibm_watson_openscale/utils/model_utils.py
ibm_watson_openscale/utils/embeddings_generation_utility.py
ibm_watson_openscale/utils/client_utils.py
ibm_watson_openscale/utils/drift_v2_utility.py
ibm_watson_openscale/utils/config_util.c
ibm_watson_openscale/utils/indirect_bias_processor.py
ibm_watson_openscale/utils/entitlement_client.py
ibm_watson_openscale/utils/request_utils.py
ibm_watson_openscale/utils/async_utils.py
ibm_watson_openscale/utils/config_util.cpython-311-darwin.so
ibm_watson_openscale/utils/constants.py
ibm_watson_openscale/utils/client_errors.py
ibm_watson_openscale/utils/usage_client.c
ibm_watson_openscale/utils/__init__.py
ibm_watson_openscale/utils/logging_support.py
ibm_watson_openscale-3.1.2.dist-info/zip-safe
ibm_watson_openscale-3.1.2.dist-info/RECORD
ibm_watson_openscale-3.1.2.dist-info/WHEEL
ibm_watson_openscale-3.1.2.dist-info/top_level.txt
ibm_watson_openscale-3.1.2.dist-info/METADATA
ibm_watson_openscale-3.1.2.dist-info/licenses/LICENSE
