Metadata-Version: 2.1
Name: ibm-watson-openscale
Version: 3.1.2
Summary: Client library for IBM Watson OpenScale
Home-page: https://github.ibm.com/watson-developer-cloud/openscale-python-sdk
Author: IBM Watson OpenScale
Author-email: kishore.patel@in.ibm.com
License: Apache 2.0
Keywords: Manage production AIwith trust and confidence in outcomeswatson,ibm
Classifier: Programming Language :: Python :: 3
Classifier: Development Status :: 4 - Beta
Classifier: Intended Audience :: Developers
Classifier: License :: OSI Approved :: Apache Software License
Classifier: Operating System :: OS Independent
Classifier: Topic :: Software Development :: Libraries :: Python Modules
Classifier: Topic :: Software Development :: Libraries :: Application Frameworks
Requires-Python: >=3.9,<3.14
License-File: LICENSE
Requires-Dist: requests <3.0,>=2.0
Requires-Dist: python-dateutil >=2.5.3
Requires-Dist: certifi >=2025.6.15
Requires-Dist: ibm-cloud-sdk-core <=3.25.0,>=3.24.0
